anydata/__init__.py
anydata/core/dataapi.py
anydata/core/endpoint.py
anydata/engine/functions.py
anydata/engine/models.py
anydata/engine/prompts/system_prompts.py
anydata/engine/prompts/user_prompts.py
anydata/exceptions.py
anydata/parsers/openapi.py
anydata/parsers/response_parser.py
anydata/schemas/core.py
anydata/schemas/openapi.py
anydata-0.1.2.dist-info/LICENSE
anydata-0.1.2.dist-info/METADATA
anydata-0.1.2.dist-info/WHEEL
anydata-0.1.2.dist-info/RECORD
