Metadata-Version: 2.1
Name: anydata
Version: 0.1.2
Summary: Smart framework to interact with and fetch data from REST APIs.
License: Apache 2.0
Author: Erich Silva
Author-email: erich@esilva.io
Requires-Python: >=3.9,<4.0
Classifier: License :: Other/Proprietary License
Classifier: Programming Language :: Python :: 3
Classifier: Programming Language :: Python :: 3.9
Classifier: Programming Language :: Python :: 3.10
Classifier: Programming Language :: Python :: 3.11
Classifier: Programming Language :: Python :: 3.12
Provides-Extra: guidance
Requires-Dist: dataclasses-json (>=0.6.4,<0.7.0)
Requires-Dist: guidance (==0.1.13) ; extra == "guidance"
Requires-Dist: pandas (>=2.0.0,<3.0.0)
Requires-Dist: pyyaml (>=6.0.1,<7.0.0)
Requires-Dist: requests (>=2.31.0,<3.0.0)
